{"_type":"export","__export_format":4,"__export_date":"2020-03-11T12:15:24.372Z","__export_source":"insomnia.desktop.app:v7.0.3","resources":[{"_id":"req_a8410be873954a7e996e8ad0a5386b54","authentication":{},"body":{},"created":1583917353576,"description":"","headers":[],"isPrivate":false,"metaSortKey":-1583917353576,"method":"GET","modified":1583917353576,"name":"Delete","parameters":[],"parentId":"fld_9cd392e44cfb47c9b3582b3f2d11016a","settingDisableRenderRequestBody":false,"settingEncodeUrl":true,"settingRebuildPath":true,"settingSendCookies":true,"settingStoreCookies":true,"url":"","_type":"request"},{"_id":"fld_9cd392e44cfb47c9b3582b3f2d11016a","created":1583917269845,"description":"","environment":{},"environmentPropertyOrder":null,"metaSortKey":-1583917269845,"modified":1583917269845,"name":"Notifications","parentId":"wrk_523ecc0e87db431395f69b39f57b1d28","_type":"request_group"},{"_id":"wrk_523ecc0e87db431395f69b39f57b1d28","created":1583917216030,"description":"","modified":1583917216030,"name":"Task Management","parentId":null,"_type":"workspace"},{"_id":"req_89d99f8eff674a95acf0c402ba19a624","authentication":{},"body":{},"created":1583917348679,"description":"","headers":[],"isPrivate":false,"metaSortKey":-1583917348679,"method":"GET","modified":1583917348679,"name":"List","parameters":[],"parentId":"fld_9cd392e44cfb47c9b3582b3f2d11016a","settingDisableRenderRequestBody":false,"settingEncodeUrl":true,"settingRebuildPath":true,"settingSendCookies":true,"settingStoreCookies":true,"url":"","_type":"request"},{"_id":"req_705915570e34466abb59d6334642c47b","authentication":{},"body":{},"created":1583917296849,"description":"","headers":[],"isPrivate":false,"metaSortKey":-1583917310049,"method":"GET","modified":1583928743067,"name":"List","parameters":[],"parentId":"fld_7cbbadc6bbf14d15b773b2617f795ce5","settingDisableRenderRequestBody":false,"settingEncodeUrl":true,"settingRebuildPath":true,"settingSendCookies":true,"settingStoreCookies":true,"url":"{{api}}:{{port}}/api/v1/group","_type":"request"},{"_id":"fld_7cbbadc6bbf14d15b773b2617f795ce5","created":1583917264683,"description":"","environment":{},"environmentPropertyOrder":null,"metaSortKey":-1583917264683,"modified":1583917264683,"name":"Group","parentId":"wrk_523ecc0e87db431395f69b39f57b1d28","_type":"request_group"},{"_id":"req_17694cf4a90042bd883be0a59e70106a","authentication":{},"body":{"mimeType":"application/json","text":"{\n  \"name\": \"Introduction to Golang 2\",\n  \"description\": \"Come join us for a chance to learn how golang works and get to eventually try it out\"\n}"},"created":1583917299966,"description":"","headers":[{"id":"pair_353ecd7670484e63a328ad10721d9821","name":"Content-Type","value":"application/json"}],"isPrivate":false,"metaSortKey":-1583917310024,"method":"POST","modified":1583928800234,"name":"Create","parameters":[],"parentId":"fld_7cbbadc6bbf14d15b773b2617f795ce5","settingDisableRenderRequestBody":false,"settingEncodeUrl":true,"settingRebuildPath":true,"settingSendCookies":true,"settingStoreCookies":true,"url":"{{api}}:{{port}}/api/v1/group","_type":"request"},{"_id":"req_7049a649dc494dfa9c1807f27c02b274","authentication":{},"body":{},"created":1583917302934,"description":"","headers":[],"isPrivate":false,"metaSortKey":-1583917310011.5,"method":"GET","modified":1583928754453,"name":"Read","parameters":[],"parentId":"fld_7cbbadc6bbf14d15b773b2617f795ce5","settingDisableRenderRequestBody":false,"settingEncodeUrl":true,"settingRebuildPath":true,"settingSendCookies":true,"settingStoreCookies":true,"url":"{{api}}:{{port}}/api/v1/group/1","_type":"request"},{"_id":"req_778eb25b482b4d32a0dd9c5abbe86178","authentication":{},"body":{"mimeType":"application/json","text":"{\n  \"id\": \"1\",\n  \"name\": \"Introduction to Golang 1\",\n  \"description\": \"Come join us for a chance to learn how golang works and get to eventually try it out\"\n}"},"created":1583917307299,"description":"","headers":[{"id":"pair_057164f66a2b4ca9870b340270e73390","name":"Content-Type","value":"application/json"}],"isPrivate":false,"metaSortKey":-1583917310005.25,"method":"PATCH","modified":1583928780691,"name":"Update","parameters":[],"parentId":"fld_7cbbadc6bbf14d15b773b2617f795ce5","settingDisableRenderRequestBody":false,"settingEncodeUrl":true,"settingRebuildPath":true,"settingSendCookies":true,"settingStoreCookies":true,"url":"{{api}}:{{port}}/api/v1/group/1","_type":"request"},{"_id":"req_b7f9b727e73245b390cee695a524a8aa","authentication":{},"body":{},"created":1583917309999,"description":"","headers":[],"isPrivate":false,"metaSortKey":-1583917309999,"method":"DELETE","modified":1583928819392,"name":"Delete","parameters":[],"parentId":"fld_7cbbadc6bbf14d15b773b2617f795ce5","settingDisableRenderRequestBody":false,"settingEncodeUrl":true,"settingRebuildPath":true,"settingSendCookies":true,"settingStoreCookies":true,"url":"{{api}}:{{port}}/api/v1/group/1","_type":"request"},{"_id":"req_cd769c93a0a944be8441461d6367bed2","authentication":{},"body":{},"created":1583917316858,"description":"","headers":[],"isPrivate":false,"metaSortKey":-1583917330592,"method":"GET","modified":1583928717730,"name":"List","parameters":[],"parentId":"fld_fecd20fe69604046b0e7bfc638e2238e","settingDisableRenderRequestBody":false,"settingEncodeUrl":true,"settingRebuildPath":true,"settingSendCookies":true,"settingStoreCookies":true,"url":"","_type":"request"},{"_id":"fld_fecd20fe69604046b0e7bfc638e2238e","created":1583917260059,"description":"","environment":{},"environmentPropertyOrder":null,"metaSortKey":-1583917260060,"modified":1583917260059,"name":"Task","parentId":"wrk_523ecc0e87db431395f69b39f57b1d28","_type":"request_group"},{"_id":"req_be9f719f98824bfd8343f53e88b4214e","authentication":{},"body":{},"created":1583917327071,"description":"","headers":[],"isPrivate":false,"metaSortKey":-1583917330579.5,"method":"GET","modified":1583928724889,"name":"Create","parameters":[],"parentId":"fld_fecd20fe69604046b0e7bfc638e2238e","settingDisableRenderRequestBody":false,"settingEncodeUrl":true,"settingRebuildPath":true,"settingSendCookies":true,"settingStoreCookies":true,"url":"","_type":"request"},{"_id":"req_ce11120144804511840afc7c380fbaa8","authentication":{},"body":{},"created":1583917319784,"description":"","headers":[],"isPrivate":false,"metaSortKey":-1583917330567,"method":"GET","modified":1583928719383,"name":"Read","parameters":[],"parentId":"fld_fecd20fe69604046b0e7bfc638e2238e","settingDisableRenderRequestBody":false,"settingEncodeUrl":true,"settingRebuildPath":true,"settingSendCookies":true,"settingStoreCookies":true,"url":"","_type":"request"},{"_id":"req_ca3a01363f6e4ef88ff61c2ec7d278d4","authentication":{},"body":{},"created":1583917322989,"description":"","headers":[],"isPrivate":false,"metaSortKey":-1583917330554.5,"method":"GET","modified":1583928720328,"name":"Update","parameters":[],"parentId":"fld_fecd20fe69604046b0e7bfc638e2238e","settingDisableRenderRequestBody":false,"settingEncodeUrl":true,"settingRebuildPath":true,"settingSendCookies":true,"settingStoreCookies":true,"url":"","_type":"request"},{"_id":"req_a4b82a19f54442b28a0a992b04619c85","authentication":{},"body":{},"created":1583917330542,"description":"","headers":[],"isPrivate":false,"metaSortKey":-1583917330542,"method":"GET","modified":1583917330542,"name":"Delete","parameters":[],"parentId":"fld_fecd20fe69604046b0e7bfc638e2238e","settingDisableRenderRequestBody":false,"settingEncodeUrl":true,"settingRebuildPath":true,"settingSendCookies":true,"settingStoreCookies":true,"url":"","_type":"request"},{"_id":"req_091bd07258034e028aa9b6e044062107","authentication":{},"body":{},"created":1583917250468,"description":"","headers":[],"isPrivate":false,"metaSortKey":-1583917250468,"method":"GET","modified":1583917250468,"name":"Info","parameters":[],"parentId":"fld_c69764a02c7b4c12b3e2e1e0f02df909","settingDisableRenderRequestBody":false,"settingEncodeUrl":true,"settingRebuildPath":true,"settingSendCookies":true,"settingStoreCookies":true,"url":"","_type":"request"},{"_id":"fld_c69764a02c7b4c12b3e2e1e0f02df909","created":1583917233990,"description":"","environment":{},"environmentPropertyOrder":null,"metaSortKey":-1583917233990,"modified":1583917233990,"name":"Auth","parentId":"wrk_523ecc0e87db431395f69b39f57b1d28","_type":"request_group"},{"_id":"req_afc72cf9f97d49e79d2ba06062258afa","authentication":{},"body":{},"created":1583917246639,"description":"","headers":[],"isPrivate":false,"metaSortKey":-1583917246639,"method":"GET","modified":1583917246639,"name":"Register","parameters":[],"parentId":"fld_c69764a02c7b4c12b3e2e1e0f02df909","settingDisableRenderRequestBody":false,"settingEncodeUrl":true,"settingRebuildPath":true,"settingSendCookies":true,"settingStoreCookies":true,"url":"","_type":"request"},{"_id":"req_04efaa1a99fe40e79a181b28df53d48d","authentication":{},"body":{"mimeType":"application/json","text":"{\n\t\"username\": \"duy\",\n\t\"password\": \"1\"\n}"},"created":1583917236895,"description":"","headers":[{"id":"pair_c273a49589a04cdd876a5f66eb2b3da1","name":"Content-Type","value":"application/json"}],"isPrivate":false,"metaSortKey":-1583917236895,"method":"POST","modified":1583919680989,"name":"Login","parameters":[],"parentId":"fld_c69764a02c7b4c12b3e2e1e0f02df909","settingDisableRenderRequestBody":false,"settingEncodeUrl":true,"settingRebuildPath":true,"settingSendCookies":true,"settingStoreCookies":true,"url":"{{api}}:{{port}}/api/v1/auth/login","_type":"request"},{"_id":"env_2b17fb0422adf19cd38943006720e69b9649ed2c","color":null,"created":1583917216112,"data":{"api":"localhost","port":8080,"token":"ádasdasdas"},"dataPropertyOrder":{"&":["api","port","token"]},"isPrivate":false,"metaSortKey":1583917216112,"modified":1583919623299,"name":"Base Environment","parentId":"wrk_523ecc0e87db431395f69b39f57b1d28","_type":"environment"},{"_id":"jar_2b17fb0422adf19cd38943006720e69b9649ed2c","cookies":[],"created":1583917216116,"modified":1583917216116,"name":"Default Jar","parentId":"wrk_523ecc0e87db431395f69b39f57b1d28","_type":"cookie_jar"}]}